mitosheet_helper_4c2a/__init__.py
mitosheet_helper_4c2a-0.0.1.dist-info/licenses/LICENSE
mitosheet_helper_4c2a-0.0.1.dist-info/METADATA
mitosheet_helper_4c2a-0.0.1.dist-info/WHEEL
mitosheet_helper_4c2a-0.0.1.dist-info/top_level.txt
mitosheet_helper_4c2a-0.0.1.dist-info/RECORD
