Metadata-Version: 2.4
Name: mitosheet_helper_4c2a
Version: 0.0.1
Summary: A helper package for mitosheet.
Author-email: Aaron Diamond-Reivich <aaron@sagacollab.com>
License: The Mito Pro license (the “Pro License”)
Project-URL: Homepage, https://github.com/mito-ds/monorepo
Project-URL: Bug Tracker, https://github.com/mito-ds/monorepo/issues
Classifier: Programming Language :: Python :: 3
Classifier: Operating System :: OS Independent
Requires-Python: >=3.6
License-File: LICENSE
Dynamic: license-file
